MANIFEST.in
setup.py
conway/__init__.py
conway/gol.py
conway/splash
gol.egg-info/PKG-INFO
gol.egg-info/SOURCES.txt
gol.egg-info/dependency_links.txt
gol.egg-info/entry_points.txt
gol.egg-info/pbr.json
gol.egg-info/top_level.txt