Metadata-Version: 1.1
Name: gol
Version: 1.0.0
Summary: Curses implementation of Conway's Game Of Life with an evolutionary twist
Home-page: https://github.com/iiSeymour/game-of-life
Author: Chris Seymour
Author-email: chris.j.seymour@hotmail.com
License: MIT
Platform: UNKNOWN
Classifier: Development Status :: 5 - Production/Stable
Classifier: Environment :: Console :: Curses
Classifier: Intended Audience :: Developers
Classifier: License :: OSI Approved :: MIT License
Classifier: Natural Language :: English
Classifier: Operating System :: POSIX :: Linux
Classifier: Topic :: Games/Entertainment :: Simulation
Classifier: Programming Language :: Python
